bash-colors/__init__.py
bash-colors/colors.py
bashcolors/__init__.py
bashcolors/colors.py
bashcolors-0.1.dist-info/METADATA
bashcolors-0.1.dist-info/WHEEL
bashcolors-0.1.dist-info/top_level.txt
bashcolors-0.1.dist-info/RECORD
