Metadata-Version: 2.1
Name: bashcolors
Version: 0.1
Summary: Easy tool to add colors to your terminal app!
Author: ilpy
Author-email: <ilpy@proton.me>
